pyspark_data_toolkit/audit_utils.py
pyspark_data_toolkit/dataframe_utils.py
pyspark_data_toolkit/datetime_utils.py
pyspark_data_toolkit/delta_table_utils.py
pyspark_data_toolkit/diff_utils.py
pyspark_data_toolkit/json_utils.py
pyspark_data_toolkit/normalization_utils.py
pyspark_data_toolkit/profiling_utils.py
pyspark_data_toolkit/schema_utils.py
pyspark_data_toolkit/union_utils.py
pyspark_data_toolkit/window_utils.py
pyspark_data_toolkit-0.2.44.dist-info/licenses/LICENSE
pyspark_data_toolkit-0.2.44.dist-info/METADATA
pyspark_data_toolkit-0.2.44.dist-info/WHEEL
pyspark_data_toolkit-0.2.44.dist-info/top_level.txt
pyspark_data_toolkit-0.2.44.dist-info/RECORD
