Metadata-Version: 2.4
Name: pyspark-data-toolkit
Version: 0.2.44
Summary: Modular toolkit for Data Engineering with PySpark and Delta Lake — schema management, auditing, profiling, normalization, JSON handling, window functions, and Delta Lake operations.
Author-email: Thaissa Ferreira <thaissa.teodoro@hotmail.com>
License-Expression: MIT
Classifier: Development Status :: 4 - Beta
Classifier: Intended Audience :: Developers
Classifier: Programming Language :: Python :: 3
Classifier: Operating System :: OS Independent
Classifier: Topic :: Software Development :: Libraries
Requires-Python: >=3.8
License-File: LICENSE
Requires-Dist: logging-metrics>=0.1.2
Requires-Dist: pyspark>=3.5.0
Requires-Dist: delta-spark>=2.0.0
Requires-Dist: IPython
Provides-Extra: dev
Requires-Dist: pytest>=7.0.0; extra == "dev"
Requires-Dist: pytest-cov>=4.0.0; extra == "dev"
Requires-Dist: pytest-xdist>=3.0.0; extra == "dev"
Requires-Dist: pytest-mock>=3.10.0; extra == "dev"
Requires-Dist: py4j>=0.10.9; extra == "dev"
Requires-Dist: coverage>=6.0.0; extra == "dev"
Requires-Dist: faker>=18.0.0; extra == "dev"
Requires-Dist: hypothesis>=6.0.0; extra == "dev"
Requires-Dist: black>=22.0.0; extra == "dev"
Requires-Dist: flake8>=5.0.0; extra == "dev"
Requires-Dist: delta-table>=2.4.0; extra == "dev"
Dynamic: license-file
